hvpdb_backup/__init__.py
hvpdb_backup-0.1.0.dist-info/METADATA
hvpdb_backup-0.1.0.dist-info/WHEEL
hvpdb_backup-0.1.0.dist-info/entry_points.txt
hvpdb_backup-0.1.0.dist-info/top_level.txt
hvpdb_backup-0.1.0.dist-info/RECORD
