Metadata-Version: 2.4
Name: hvpdb-backup
Version: 0.1.0
Summary: Backup & Restore Plugin for HVPDB
Requires-Dist: hvpdb
Dynamic: requires-dist
Dynamic: summary
